multimodars/__init__.py
multimodars/_converters.py
multimodars/_wrappers.py
multimodars/ccta/__init__.py
multimodars/ccta/adjust_ccta.py
multimodars/io/__init__.py
multimodars/io/read_geometrical.py
multimodars/io/write_geometries.py
multimodars/multimodars.cpython-313-aarch64-linux-gnu.so
multimodars-0.2.1.dist-info/METADATA
multimodars-0.2.1.dist-info/WHEEL
multimodars-0.2.1.dist-info/licenses/LICENSE
multimodars-0.2.1.dist-info/RECORD
