Metadata-Version: 2.4
Name: multimodars
Version: 0.2.1
Classifier: Programming Language :: Rust
Classifier: Programming Language :: Python :: Implementation :: CPython
Classifier: Programming Language :: Python :: Implementation :: PyPy
Classifier: License :: OSI Approved :: MIT License
Requires-Dist: numpy>=2.0.0,<3.0.0
Requires-Dist: trimesh>=4.8.0
Requires-Dist: pyglet<2
Requires-Dist: sphinx>=8.0,<9.0 ; extra == 'docs'
Requires-Dist: sphinx-rtd-theme ; extra == 'docs'
Requires-Dist: sphinx-autodoc-typehints ; extra == 'docs'
Requires-Dist: myst-parser ; extra == 'docs'
Requires-Dist: maturin>=1.7,<2.0 ; extra == 'docs'
Requires-Dist: furo ; extra == 'docs'
Requires-Dist: pytest>=9.0.2 ; extra == 'test'
Requires-Dist: pytest-cov ; extra == 'test'
Requires-Dist: ruff ; extra == 'test'
Requires-Dist: black ; extra == 'test'
Provides-Extra: docs
Provides-Extra: test
License-File: LICENSE
Summary: A Rust-powered cardiac multi-image modality fusion package
Author: Anselm W. Stark
License-Expression: MIT
Requires-Python: >=3.8
Project-URL: Homepage, https://github.com/yungselm/multimoda-rs
Project-URL: Issues, https://github.com/yungselm/multimoda-rs/issues
